[
  {
    "translator": "Dr Farhat Hashmi",
    "words": [
      {
        "arabic": "فَتِلۡکَ",
        "urdu": "تو یہ"
      },
      {
        "arabic": "بُیُوۡتُہُمۡ",
        "urdu": "ان کے گھر ہیں"
      },
      {
        "arabic": "خَاوِیَۃًۢ",
        "urdu": "گرے ہوئے"
      },
      {
        "arabic": "بِمَا",
        "urdu": "بوجہ اس کے جو"
      },
      {
        "arabic": "ظَلَمُوۡا",
        "urdu": "انہوں نے ظلم کیا"
      },
      {
        "arabic": "اِنَّ",
        "urdu": "یقیناً"
      },
      {
        "arabic": "فِیۡ ذٰلِکَ",
        "urdu": "اس میں"
      },
      {
        "arabic": "لَاٰیَۃً",
        "urdu": "البتہ ایک نشانی ہے"
      },
      {
        "arabic": "لِّقَوۡمٍ",
        "urdu": "ان لوگوں کے لیے"
      },
      {
        "arabic": "یَّعۡلَمُوۡنَ",
        "urdu": "جو علم رکھتے ہیں"
      }
    ]
  },
  {
    "translator": "Nighat Hashmi",
    "words": [
      {
        "arabic": "فَتِلۡکَ",
        "urdu": "پھر یہ"
      },
      {
        "arabic": "بُیُوۡتُہُمۡ",
        "urdu": "گھر اُن کے"
      },
      {
        "arabic": "خَاوِیَۃًۢ",
        "urdu": "ویران پڑے ہیں"
      },
      {
        "arabic": "بِمَا",
        "urdu": "بوجہ اس کے جو"
      },
      {
        "arabic": "ظَلَمُوۡا",
        "urdu": "اُنہوں نے ظلم کیا"
      },
      {
        "arabic": "اِنَّ",
        "urdu": "بلاشبہ"
      },
      {
        "arabic": "فِیۡ ذٰلِکَ",
        "urdu": "اس میں"
      },
      {
        "arabic": "لَاٰیَۃً",
        "urdu": "یقیناً ایک نشانی ہے"
      },
      {
        "arabic": "لِّقَوۡمٍ",
        "urdu": "ایسی قوم کے لیے"
      },
      {
        "arabic": "یَّعۡلَمُوۡنَ",
        "urdu": "وہ جانتے ہیں"
      }
    ]
  }
]