[
  {
    "language": "Urdu",
    "translator": "Muhammad Junagarhi",
    "text": "اور عاد بیحد تیز و تند ہوا سے غارت کر دیئے گئے ۔"
  },
  {
    "language": "Urdu",
    "translator": "Dr. Israr Ahmad",
    "text": "اور عاد ہلاک کردیے گئے ایک جھکڑ ّوالی تیز آندھی سے۔"
  },
  {
    "language": "Urdu",
    "translator": "Abdul Rehman Killani",
    "text": "رہے عاد تو وہ سناٹے کی سخت آندھی سے ہلاک کیے گئے"
  },
  {
    "language": "Urdu",
    "translator": "Fateh Muhammad Jalandhari",
    "text": "رہے عاد تو ان کا نہایت تیز آندھی سے ستیاناس کردیا گیا"
  },
  {
    "language": "Urdu",
    "translator": "Abdul Salam Bhutvi",
    "text": "اور جو عاد تھے وہ سخت ٹھنڈی، تند آندھی کے ساتھ ہلاک کردیے گئے، جو قابو سے باہر ہونے والی تھی۔"
  },
  {
    "language": "Urdu",
    "translator": "Ustaza Nighat Hashmi",
    "text": "اور جو عاد تھے تووہ سخت ٹھنڈی،تندوتیز آندھی سے ہلاک کردیے گئے جوقابوسے باہرہونے والی تھی۔"
  },
  {
    "language": "Urdu",
    "translator": "Amin Ahsan Islahi",
    "text": "اور رہے عاد تو وہ ایک بے قابو باد تند سے برباد ہوئے ۔"
  },
  {
    "language": "Urdu",
    "translator": "Dr. Muhammad Aslam Siddiqui",
    "text": "رہے عاد، تو وہ ایک بڑی شدید طوفانی آندھی سے تباہ کردیئے گئے۔"
  },
  {
    "language": "Urdu",
    "translator": "Hussain Najfi",
    "text": "اور بنی عاد ایک حد سے زیادہ تیز و تند  ( اور سرد )  آندھی سے ہلاک کئے گئے ۔"
  },
  {
    "language": "Urdu",
    "translator": "Allama Jawadi",
    "text": "اور عاد کو انتہائی تیز و تند آندھی سے برباد کردیا گیا"
  },
  {
    "language": "Urdu",
    "translator": "Abul A'la Maudoodi",
    "text": "اور عادایک بڑی شدید طوفانی آندھی سے تباہ کر دیے گئے ۔"
  },
  {
    "language": "Urdu",
    "translator": "Mufti Naeem",
    "text": "اور رہے عاد تو وہ تند و تیز انتہائی ٹھنڈی ہوا سے ہلاک کردیے گئے ۔"
  },
  {
    "language": "Urdu",
    "translator": "Mufti Taqi Usmani",
    "text": "اور جو عاد کے لوگ تھے ،  انہیں ایک ایسی بے قابو طوفانی ہوا سے ہلاک کیا گیا ۔"
  },
  {
    "language": "Urdu",
    "translator": "Riffat Aijaz",
    "text": "تو عاد کا نہایت تیز آندھی سے ستیاناس کردیا گیا"
  },
  {
    "language": "Urdu",
    "translator": "Noor ul Amin",
    "text": "قوم عاد کے لوگ ایک تیزوتندآندھی کے ذریعے ہلاک کردئیے گئے"
  },
  {
    "language": "Urdu",
    "translator": "Ahmad Raza Khan | Kanzul Eman",
    "text": "اور رہے عاد وہ ہلاک کیے گئے نہایت سخت گرجتی آندھی سے ،"
  },
  {
    "language": "Urdu",
    "translator": "Dr. Tahir ul Qadri",
    "text": "اور رہے قومِ عاد کے لوگ! تو وہ  ( بھی )  ایسی تیز آندھی سے ہلاک کر دئیے گئے جو انتہائی سرد نہایت گرج دار تھی"
  },
  {
    "language": "Hindi",
    "translator": "Moulana Palanpuri",
    "text": "और रहे आद, तो वे एक अनियंत्रित प्रचंड वायु से विनष्ट कर दिए गए"
  },
  {
    "language": "English Sahih International",
    "translator": "",
    "text": "And as for 'Aad, they were destroyed by a screaming, violent wind"
  },
  {
    "language": "English",
    "translator": "Muhammad Junagarhi",
    "text": "And as for 'Aad, they were destroyed by a screaming, violent wind"
  },
  {
    "language": "English",
    "translator": "Abul A'la Maudoodi",
    "text": "and the Ad were destroyed by a furiously raging wind-storm"
  },
  {
    "language": "English",
    "translator": "Safi-ur-Rehman Mubarakpuri",
    "text": "And as for `Ad, they were destroyed by a wind, Sarsar `Atiyah!"
  },
  {
    "language": "English",
    "translator": "Muhammad William Pickthall",
    "text": "And as for A'ad, they were destroyed by a fierce roaring wind,"
  },
  {
    "language": "English",
    "translator": "Muhammad Sarwar",
    "text": "The Ads were destroyed by a swift, destructive gale"
  },
  {
    "language": "English",
    "translator": "Muhammad Habib Shakir",
    "text": "And as to Ad, they were destroyed by a roaring, violent blast."
  },
  {
    "language": "English",
    "translator": "Abdullah Yusuf Ali",
    "text": "And the 'Ad, they were destroyed by a furious Wind, exceedingly violent;"
  },
  {
    "language": "English",
    "translator": "Mufti Taqi Usmani",
    "text": "And as for Aad, they were destroyed by a violent windstorm"
  }
]