[
  {
    "translator": "Dr Farhat Hashmi",
    "words": [
      {
        "arabic": "وَاِذۡ",
        "urdu": "اور جب"
      },
      {
        "arabic": "یَعِدُکُمُ",
        "urdu": "وعدہ کررہا تھا تم سے"
      },
      {
        "arabic": "اللّٰہُ",
        "urdu": "اللہ"
      },
      {
        "arabic": "اِحۡدَی",
        "urdu": "ایک کا"
      },
      {
        "arabic": "الطَّآئِفَتَیۡنِ",
        "urdu": "دو گروہوں میں سے"
      },
      {
        "arabic": "اَنَّہَا",
        "urdu": "بیشک وہ"
      },
      {
        "arabic": "لَکُمۡ",
        "urdu": "تمہارے لیے ہے"
      },
      {
        "arabic": "وَتَوَدُّوۡنَ",
        "urdu": "اور تم چاہتے تھے"
      },
      {
        "arabic": "اَنَّ",
        "urdu": "بیشک"
      },
      {
        "arabic": "غَیۡرَ",
        "urdu": "بغیر"
      },
      {
        "arabic": "ذَاتِ الشَّوۡکَۃِ",
        "urdu": "ہتھیار  والا"
      },
      {
        "arabic": "تَکُوۡنُ",
        "urdu": "ہوجائے"
      },
      {
        "arabic": "لَکُمۡ",
        "urdu": "تمہارے لیے"
      },
      {
        "arabic": "وَ یُرِیۡدُ",
        "urdu": "اور چاہتا تھا"
      },
      {
        "arabic": "اللّٰہُ",
        "urdu": "اللہ"
      },
      {
        "arabic": "اَنۡ",
        "urdu": "کہ"
      },
      {
        "arabic": "یُّحِقَّ",
        "urdu": "وہ ثابت کردے"
      },
      {
        "arabic": "الۡحَقَّ",
        "urdu": "حق کو"
      },
      {
        "arabic": "بِکَلِمٰتِہٖ",
        "urdu": "اپنے کلمات سے"
      },
      {
        "arabic": "وَیَقۡطَعَ",
        "urdu": "اور وہ کاٹ ڈالے"
      },
      {
        "arabic": "دَابِرَ",
        "urdu": "جڑ"
      },
      {
        "arabic": "الۡکٰفِرِیۡنَ",
        "urdu": "کافروں کی"
      }
    ]
  },
  {
    "translator": "Nighat Hashmi",
    "words": [
      {
        "arabic": "وَاِذۡ",
        "urdu": "اور جب"
      },
      {
        "arabic": "یَعِدُکُمُ",
        "urdu": "وعدہ کر رہا تھا تم سے"
      },
      {
        "arabic": "اللّٰہُ",
        "urdu": "اللہ تعالیٰ"
      },
      {
        "arabic": "اِحۡدَی",
        "urdu": "ایک کا"
      },
      {
        "arabic": "الطَّآئِفَتَیۡنِ",
        "urdu": "دو گروہوں میں سے"
      },
      {
        "arabic": "اَنَّہَا",
        "urdu": "یقیناً وہ"
      },
      {
        "arabic": "لَکُمۡ",
        "urdu": "تمہارے لیے ہے"
      },
      {
        "arabic": "وَتَوَدُّوۡنَ",
        "urdu": "اور تم چاہتے تھے"
      },
      {
        "arabic": "اَنَّ",
        "urdu": "یقیناً"
      },
      {
        "arabic": "غَیۡرَ",
        "urdu": "بغیر"
      },
      {
        "arabic": "ذَاتِ الشَّوۡکَۃِ",
        "urdu": "کا نٹے والا ( غیر مسلح گروہ )"
      },
      {
        "arabic": "تَکُوۡنُ",
        "urdu": "ہو"
      },
      {
        "arabic": "لَکُمۡ",
        "urdu": "تمہارے لئے"
      },
      {
        "arabic": "وَ یُرِیۡدُ",
        "urdu": "اور ارادہ کر چکا تھا"
      },
      {
        "arabic": "اللّٰہُ",
        "urdu": "اللہ تعالیٰ"
      },
      {
        "arabic": "اَنۡ",
        "urdu": "یہ کہ"
      },
      {
        "arabic": "یُّحِقَّ",
        "urdu": "وہ حق کر دکھا ئے"
      },
      {
        "arabic": "الۡحَقَّ",
        "urdu": "حق کو"
      },
      {
        "arabic": "بِکَلِمٰتِہٖ",
        "urdu": "ساتھ اپنی باتوں کے"
      },
      {
        "arabic": "وَیَقۡطَعَ",
        "urdu": "اور وہ کاٹ دے"
      },
      {
        "arabic": "دَابِرَ",
        "urdu": "جڑ"
      },
      {
        "arabic": "الۡکٰفِرِیۡنَ",
        "urdu": "کافروں کی"
      }
    ]
  }
]