{
  "verseNumber": 21,
  "verse": "قَالَ نُوۡحٌ  رَّبِّ اِنَّہُمۡ عَصَوۡنِیۡ وَ اتَّبَعُوۡا مَنۡ لَّمۡ  یَزِدۡہُ  مَالُہٗ وَ وَلَدُہٗۤ  اِلَّا خَسَارًا ﴿ۚ۲۱﴾",
  "verseUrdu": "نوح  ( علیہ السلام )  نے کہا اے میرے پروردگار! ان لوگوں نے میری تو نافرمانی کی اور ایسوں کی فرمانبرداری کی جن کے مال و اولاد نے  ( یقیناً )  نقصان ہی میں بڑھایا ہے ۔",
  "verseEnglish": "Noah said, \"My Lord, indeed they have disobeyed me and followed him whose wealth and children will not increase him except in loss.",
  "verseAudioUrl": "https://everyayah.com/data/Saood_ash-Shuraym_128kbps/071021.mp3"
}